yta_stock_common/__init__.py
yta_stock_common-0.0.2.dist-info/licenses/LICENSE
yta_stock_common-0.0.2.dist-info/METADATA
yta_stock_common-0.0.2.dist-info/WHEEL
yta_stock_common-0.0.2.dist-info/RECORD
