Metadata-Version: 2.4
Name: yta-stock-common
Version: 0.0.2
Summary: Youtube Autonomous Stock Common module
License-File: LICENSE
Author: danialcala94
Author-email: danielalcalavalera@gmail.com
Requires-Python: ==3.9
Classifier: Programming Language :: Python :: 3
Classifier: Programming Language :: Python :: 3.9
Requires-Dist: yta_constants (>=0.0.1,<1.0.0)
Requires-Dist: yta_programming (>=0.0.1,<1.0.0)
